libname/__init__.py
libname/hello.py
helloparamkusham-0.0.4.dist-info/METADATA
helloparamkusham-0.0.4.dist-info/WHEEL
helloparamkusham-0.0.4.dist-info/top_level.txt
helloparamkusham-0.0.4.dist-info/RECORD
