Metadata-Version: 2.1
Name: helloparamkusham
Version: 0.0.4
Summary: A Basic hello package
Home-page: UNKNOWN
Author: srujan
Author-email: <srujan@gmail.com>
License: UNKNOWN
Keywords: python,video,stream,video stream,camera stream,sockets
Platform: UNKNOWN
Classifier: Development Status :: 1 - Planning
Classifier: Intended Audience :: Developers
Classifier: Programming Language :: Python :: 3
Classifier: Operating System :: Unix
Classifier: Operating System :: MacOS :: MacOS X
Classifier: Operating System :: Microsoft :: Windows
